doku/__init__.py
doku/client.py
doku/config_manager.py
doku/context.py
doku/cookie_safe_transport.py
doku/cookie_transport.py
doku/main.py
doku-0.1.8.dist-info/LICENSE
doku-0.1.8.dist-info/METADATA
doku-0.1.8.dist-info/WHEEL
doku-0.1.8.dist-info/entry_points.txt
doku-0.1.8.dist-info/top_level.txt
doku-0.1.8.dist-info/zip-safe
doku-0.1.8.dist-info/RECORD
