Metadata-Version: 2.1
Name: doku
Version: 0.1.8
Summary: UNKNOWN
Home-page: https://github.com/yitsushi/doku
Author: Balazs Nadasdi
Author-email: balazs.nadasdi@cheppers.com
License: UNKNOWN
Platform: UNKNOWN
Classifier: Programming Language :: Python :: 3
Classifier: License :: OSI Approved :: GNU General Public License v3 or later (GPLv3+)
Classifier: Operating System :: OS Independent
Requires-Dist: click
